{"id":"87d7ad1f-3d14-4e05-833b-145bb39d9302","type":"training","app_id":"com.nike.ntc.brand.droid","start_epoch_ms":1569637853455,"end_epoch_ms":1569638827654,"last_modified":1569638863835,"active_duration_ms":908000,"session":false,"delete_indicator":false,"summaries":[{"metric":"nikefuel","summary":"total","source":"nike.ntc.android","app_id":"com.nike.ntc.brand.droid","value":125},{"metric":"nikefuel","summary":"mean","source":"nike.ntc.android","app_id":"com.nike.ntc.brand.droid","value":8.259911894273127},{"metric":"rpe","summary":"max","source":"nike.ntc.android","app_id":"com.nike.ntc.brand.droid","value":2},{"metric":"calories","summary":"total","source":"nike.ntc.android","app_id":"com.nike.ntc.brand.droid","value":25}],"sources":["nike.ntc.android"],"tags":{"com.nike.ntc.location":"home","com.nike.ntc.workout.benchmark":"false","com.nike.ntc.workout.duration_sec":"900","com.nike.ntc.workout.equipment":"NONE","com.nike.ntc.workout.estimated_calories":"25","com.nike.ntc.workout.focus":"mobility","com.nike.ntc.workout.format":"free","com.nike.ntc.workout.id":"07854dfc-2708-3be3-bfe8-ce77e8c060dc","com.nike.ntc.workout.intensity":"low","com.nike.ntc.workout.level":"beginner","com.nike.ntc.workout.name":"Open Rotation","com.nike.ntc.workout.seotag":"Sue Falsone","com.nike.ntc.workout.type":"time based"},"change_tokens":["c87ae9c12ade8d675483a28cb9ac178fea30c92fc4d8ceb51fb3f827f3499ab6:1569638863835"],"metric_types":["rpe","calories","nikefuel"],"metrics":[{"type":"nikefuel","unit":"FUEL","source":"nike.ntc.android","appId":"com.nike.ntc.brand.droid","values":[{"start_epoch_ms":1569637853455,"end_epoch_ms":1569638827654,"value":125}]},{"type":"rpe","unit":"RATING","source":"nike.ntc.android","appId":"com.nike.ntc.brand.droid","values":[{"start_epoch_ms":1569637853455,"end_epoch_ms":1569638827654,"value":2}]},{"type":"calories","unit":"KCAL","source":"nike.ntc.android","appId":"com.nike.ntc.brand.droid","values":[{"start_epoch_ms":1569637853455,"end_epoch_ms":1569638827654,"value":25}]}],"moments":[{"key":"drill_complete","value":"42eeecc9-cee9-36af-a50f-3277cbf4a0b4","timestamp":1569637883661,"app_id":"com.nike.ntc.brand.droid","source":"nike.ntc.android"},{"key":"drill_complete","value":"42eeecc9-cee9-36af-a50f-3277cbf4a0b4","timestamp":1569637893881,"app_id":"com.nike.ntc.brand.droid","source":"nike.ntc.android"},{"key":"drill_complete","value":"4684bc18-2d48-3158-bc0e-84e05b84464a","timestamp":1569637894194,"app_id":"com.nike.ntc.brand.droid","source":"nike.ntc.android"},{"key":"drill_complete","value":"42eeecc9-cee9-36af-a50f-3277cbf4a0b4","timestamp":1569637953880,"app_id":"com.nike.ntc.brand.droid","source":"nike.ntc.android"},{"key":"drill_complete","value":"42eeecc9-cee9-36af-a50f-3277cbf4a0b4","timestamp":1569637964106,"app_id":"com.nike.ntc.brand.droid","source":"nike.ntc.android"},{"key":"drill_complete","value":"139d90fb-8a35-3fee-ae8f-12f57d286fe9","timestamp":1569637966618,"app_id":"com.nike.ntc.brand.droid","source":"nike.ntc.android"},{"key":"drill_complete","value":"42eeecc9-cee9-36af-a50f-3277cbf4a0b4","timestamp":1569638024107,"app_id":"com.nike.ntc.brand.droid","source":"nike.ntc.android"},{"key":"drill_complete","value":"42eeecc9-cee9-36af-a50f-3277cbf4a0b4","timestamp":1569638034347,"app_id":"com.nike.ntc.brand.droid","source":"nike.ntc.android"},{"key":"drill_complete","value":"dcc33f19-0ab5-3607-8fad-ea9d78cb5489","timestamp":1569638034486,"app_id":"com.nike.ntc.brand.droid","source":"nike.ntc.android"},{"key":"drill_complete","value":"42eeecc9-cee9-36af-a50f-3277cbf4a0b4","timestamp":1569638064346,"app_id":"com.nike.ntc.brand.droid","source":"nike.ntc.android"},{"key":"drill_complete","value":"42eeecc9-cee9-36af-a50f-3277cbf4a0b4","timestamp":1569638074530,"app_id":"com.nike.ntc.brand.droid","source":"nike.ntc.android"},{"key":"drill_complete","value":"a9f6174f-c1af-3c8b-827e-e31fd9e9f460","timestamp":1569638078627,"app_id":"com.nike.ntc.brand.droid","source":"nike.ntc.android"},{"key":"drill_complete","value":"42eeecc9-cee9-36af-a50f-3277cbf4a0b4","timestamp":1569638104531,"app_id":"com.nike.ntc.brand.droid","source":"nike.ntc.android"},{"key":"drill_complete","value":"42eeecc9-cee9-36af-a50f-3277cbf4a0b4","timestamp":1569638114701,"app_id":"com.nike.ntc.brand.droid","source":"nike.ntc.android"},{"key":"drill_complete","value":"53cf38fd-741a-3d69-9cd7-09c1fc7542aa","timestamp":1569638124979,"app_id":"com.nike.ntc.brand.droid","source":"nike.ntc.android"},{"key":"drill_complete","value":"42eeecc9-cee9-36af-a50f-3277cbf4a0b4","timestamp":1569638134700,"app_id":"com.nike.ntc.brand.droid","source":"nike.ntc.android"},{"key":"drill_complete","value":"42eeecc9-cee9-36af-a50f-3277cbf4a0b4","timestamp":1569638144874,"app_id":"com.nike.ntc.brand.droid","source":"nike.ntc.android"},{"key":"drill_complete","value":"ffeabcb9-f846-3718-9d0e-e562b5ef7e94","timestamp":1569638169117,"app_id":"com.nike.ntc.brand.droid","source":"nike.ntc.android"},{"key":"drill_complete","value":"42eeecc9-cee9-36af-a50f-3277cbf4a0b4","timestamp":1569638193142,"app_id":"com.nike.ntc.brand.droid","source":"nike.ntc.android"},{"key":"drill_complete","value":"42eeecc9-cee9-36af-a50f-3277cbf4a0b4","timestamp":1569638203310,"app_id":"com.nike.ntc.brand.droid","source":"nike.ntc.android"},{"key":"drill_complete","value":"63feb440-ee4f-3d4f-ba79-b9a12108f84b","timestamp":1569638206390,"app_id":"com.nike.ntc.brand.droid","source":"nike.ntc.android"},{"key":"drill_complete","value":"42eeecc9-cee9-36af-a50f-3277cbf4a0b4","timestamp":1569638233310,"app_id":"com.nike.ntc.brand.droid","source":"nike.ntc.android"},{"key":"drill_complete","value":"42eeecc9-cee9-36af-a50f-3277cbf4a0b4","timestamp":1569638265270,"app_id":"com.nike.ntc.brand.droid","source":"nike.ntc.android"},{"key":"drill_complete","value":"e68f3548-c9ec-3aed-ae74-8b9262a02feb","timestamp":1569638273146,"app_id":"com.nike.ntc.brand.droid","source":"nike.ntc.android"},{"key":"drill_complete","value":"42eeecc9-cee9-36af-a50f-3277cbf4a0b4","timestamp":1569638295271,"app_id":"com.nike.ntc.brand.droid","source":"nike.ntc.android"},{"key":"drill_complete","value":"42eeecc9-cee9-36af-a50f-3277cbf4a0b4","timestamp":1569638305482,"app_id":"com.nike.ntc.brand.droid","source":"nike.ntc.android"},{"key":"drill_complete","value":"f5f90453-2962-3faf-92ed-895888e265f3","timestamp":1569638307356,"app_id":"com.nike.ntc.brand.droid","source":"nike.ntc.android"},{"key":"drill_complete","value":"42eeecc9-cee9-36af-a50f-3277cbf4a0b4","timestamp":1569638335470,"app_id":"com.nike.ntc.brand.droid","source":"nike.ntc.android"},{"key":"drill_complete","value":"42eeecc9-cee9-36af-a50f-3277cbf4a0b4","timestamp":1569638345645,"app_id":"com.nike.ntc.brand.droid","source":"nike.ntc.android"},{"key":"drill_complete","value":"a349b942-3950-3da0-b20e-d6e833f4cc4a","timestamp":1569638347497,"app_id":"com.nike.ntc.brand.droid","source":"nike.ntc.android"},{"key":"drill_complete","value":"42eeecc9-cee9-36af-a50f-3277cbf4a0b4","timestamp":1569638375638,"app_id":"com.nike.ntc.brand.droid","source":"nike.ntc.android"},{"key":"drill_complete","value":"42eeecc9-cee9-36af-a50f-3277cbf4a0b4","timestamp":1569638385880,"app_id":"com.nike.ntc.brand.droid","source":"nike.ntc.android"},{"key":"drill_complete","value":"bc1946b6-fe1d-3f97-bac7-f0ec3fb70338","timestamp":1569638390627,"app_id":"com.nike.ntc.brand.droid","source":"nike.ntc.android"},{"key":"drill_complete","value":"42eeecc9-cee9-36af-a50f-3277cbf4a0b4","timestamp":1569638415879,"app_id":"com.nike.ntc.brand.droid","source":"nike.ntc.android"},{"key":"drill_complete","value":"42eeecc9-cee9-36af-a50f-3277cbf4a0b4","timestamp":1569638426134,"app_id":"com.nike.ntc.brand.droid","source":"nike.ntc.android"},{"key":"drill_complete","value":"502127f7-b89b-35e0-b684-14c70802ae32","timestamp":1569638430650,"app_id":"com.nike.ntc.brand.droid","source":"nike.ntc.android"},{"key":"drill_complete","value":"42eeecc9-cee9-36af-a50f-3277cbf4a0b4","timestamp":1569638456134,"app_id":"com.nike.ntc.brand.droid","source":"nike.ntc.android"},{"key":"drill_complete","value":"42eeecc9-cee9-36af-a50f-3277cbf4a0b4","timestamp":1569638466389,"app_id":"com.nike.ntc.brand.droid","source":"nike.ntc.android"},{"key":"drill_complete","value":"6b2fa117-d6a6-3de4-84cc-830371fe28b3","timestamp":1569638480717,"app_id":"com.nike.ntc.brand.droid","source":"nike.ntc.android"},{"key":"drill_complete","value":"42eeecc9-cee9-36af-a50f-3277cbf4a0b4","timestamp":1569638496388,"app_id":"com.nike.ntc.brand.droid","source":"nike.ntc.android"},{"key":"drill_complete","value":"42eeecc9-cee9-36af-a50f-3277cbf4a0b4","timestamp":1569638506313,"app_id":"com.nike.ntc.brand.droid","source":"nike.ntc.android"},{"key":"drill_complete","value":"5b4af1c8-bf84-39d5-89c3-b9371b517691","timestamp":1569638514528,"app_id":"com.nike.ntc.brand.droid","source":"nike.ntc.android"},{"key":"drill_complete","value":"42eeecc9-cee9-36af-a50f-3277cbf4a0b4","timestamp":1569638536313,"app_id":"com.nike.ntc.brand.droid","source":"nike.ntc.android"},{"key":"drill_complete","value":"42eeecc9-cee9-36af-a50f-3277cbf4a0b4","timestamp":1569638546507,"app_id":"com.nike.ntc.brand.droid","source":"nike.ntc.android"},{"key":"drill_complete","value":"bbaaa1f1-9f1e-3bd1-a9f0-b7881247ff16","timestamp":1569638548568,"app_id":"com.nike.ntc.brand.droid","source":"nike.ntc.android"},{"key":"drill_complete","value":"42eeecc9-cee9-36af-a50f-3277cbf4a0b4","timestamp":1569638576508,"app_id":"com.nike.ntc.brand.droid","source":"nike.ntc.android"},{"key":"drill_complete","value":"42eeecc9-cee9-36af-a50f-3277cbf4a0b4","timestamp":1569638598698,"app_id":"com.nike.ntc.brand.droid","source":"nike.ntc.android"},{"key":"drill_complete","value":"dedb2bef-120b-36bc-a7e4-56abca95d48b","timestamp":1569638608836,"app_id":"com.nike.ntc.brand.droid","source":"nike.ntc.android"},{"key":"drill_complete","value":"42eeecc9-cee9-36af-a50f-3277cbf4a0b4","timestamp":1569638628698,"app_id":"com.nike.ntc.brand.droid","source":"nike.ntc.android"},{"key":"drill_complete","value":"42eeecc9-cee9-36af-a50f-3277cbf4a0b4","timestamp":1569638632530,"app_id":"com.nike.ntc.brand.droid","source":"nike.ntc.android"},{"key":"drill_complete","value":"2a77a338-5a78-362e-b9ce-d6eadeca8198","timestamp":1569638633153,"app_id":"com.nike.ntc.brand.droid","source":"nike.ntc.android"},{"key":"drill_complete","value":"42eeecc9-cee9-36af-a50f-3277cbf4a0b4","timestamp":1569638636639,"app_id":"com.nike.ntc.brand.droid","source":"nike.ntc.android"},{"key":"drill_complete","value":"a88a21c6-cf2b-316d-a752-8def0dc25d1c","timestamp":1569638637293,"app_id":"com.nike.ntc.brand.droid","source":"nike.ntc.android"},{"key":"drill_complete","value":"42eeecc9-cee9-36af-a50f-3277cbf4a0b4","timestamp":1569638647089,"app_id":"com.nike.ntc.brand.droid","source":"nike.ntc.android"},{"key":"drill_complete","value":"a88a21c6-cf2b-316d-a752-8def0dc25d1c","timestamp":1569638655203,"app_id":"com.nike.ntc.brand.droid","source":"nike.ntc.android"},{"key":"drill_complete","value":"42eeecc9-cee9-36af-a50f-3277cbf4a0b4","timestamp":1569638677088,"app_id":"com.nike.ntc.brand.droid","source":"nike.ntc.android"},{"key":"drill_complete","value":"42eeecc9-cee9-36af-a50f-3277cbf4a0b4","timestamp":1569638687331,"app_id":"com.nike.ntc.brand.droid","source":"nike.ntc.android"},{"key":"drill_complete","value":"7f5f37e9-bd3b-3c2b-a117-493ee45b3767","timestamp":1569638696114,"app_id":"com.nike.ntc.brand.droid","source":"nike.ntc.android"},{"key":"drill_complete","value":"42eeecc9-cee9-36af-a50f-3277cbf4a0b4","timestamp":1569638717332,"app_id":"com.nike.ntc.brand.droid","source":"nike.ntc.android"},{"key":"drill_complete","value":"42eeecc9-cee9-36af-a50f-3277cbf4a0b4","timestamp":1569638727263,"app_id":"com.nike.ntc.brand.droid","source":"nike.ntc.android"},{"key":"drill_complete","value":"de5ec438-6cdb-38f0-ac74-9a00dcc19030","timestamp":1569638729357,"app_id":"com.nike.ntc.brand.droid","source":"nike.ntc.android"},{"key":"drill_complete","value":"42eeecc9-cee9-36af-a50f-3277cbf4a0b4","timestamp":1569638757262,"app_id":"com.nike.ntc.brand.droid","source":"nike.ntc.android"},{"key":"drill_complete","value":"42eeecc9-cee9-36af-a50f-3277cbf4a0b4","timestamp":1569638767471,"app_id":"com.nike.ntc.brand.droid","source":"nike.ntc.android"},{"key":"drill_complete","value":"bf2856b6-90fe-34a0-a349-8fbd2830753d","timestamp":1569638780497,"app_id":"com.nike.ntc.brand.droid","source":"nike.ntc.android"},{"key":"drill_complete","value":"42eeecc9-cee9-36af-a50f-3277cbf4a0b4","timestamp":1569638797465,"app_id":"com.nike.ntc.brand.droid","source":"nike.ntc.android"},{"key":"drill_complete","value":"42eeecc9-cee9-36af-a50f-3277cbf4a0b4","timestamp":1569638807655,"app_id":"com.nike.ntc.brand.droid","source":"nike.ntc.android"},{"key":"drill_complete","value":"2a77a338-5a78-362e-b9ce-d6eadeca8198","timestamp":1569638810121,"app_id":"com.nike.ntc.brand.droid","source":"nike.ntc.android"},{"key":"drill_complete","value":"42eeecc9-cee9-36af-a50f-3277cbf4a0b4","timestamp":1569638827654,"app_id":"com.nike.ntc.brand.droid","source":"nike.ntc.android"},{"key":"drill_start","value":"4684bc18-2d48-3158-bc0e-84e05b84464a","timestamp":1569637893881,"app_id":"com.nike.ntc.brand.droid","source":"nike.ntc.android"},{"key":"drill_start","value":"42eeecc9-cee9-36af-a50f-3277cbf4a0b4","timestamp":1569637894195,"app_id":"com.nike.ntc.brand.droid","source":"nike.ntc.android"},{"key":"drill_start","value":"139d90fb-8a35-3fee-ae8f-12f57d286fe9","timestamp":1569637964106,"app_id":"com.nike.ntc.brand.droid","source":"nike.ntc.android"},{"key":"drill_start","value":"42eeecc9-cee9-36af-a50f-3277cbf4a0b4","timestamp":1569637966618,"app_id":"com.nike.ntc.brand.droid","source":"nike.ntc.android"},{"key":"drill_start","value":"dcc33f19-0ab5-3607-8fad-ea9d78cb5489","timestamp":1569638034347,"app_id":"com.nike.ntc.brand.droid","source":"nike.ntc.android"},{"key":"drill_start","value":"42eeecc9-cee9-36af-a50f-3277cbf4a0b4","timestamp":1569638034486,"app_id":"com.nike.ntc.brand.droid","source":"nike.ntc.android"},{"key":"drill_start","value":"a9f6174f-c1af-3c8b-827e-e31fd9e9f460","timestamp":1569638074530,"app_id":"com.nike.ntc.brand.droid","source":"nike.ntc.android"},{"key":"drill_start","value":"42eeecc9-cee9-36af-a50f-3277cbf4a0b4","timestamp":1569638078628,"app_id":"com.nike.ntc.brand.droid","source":"nike.ntc.android"},{"key":"drill_start","value":"53cf38fd-741a-3d69-9cd7-09c1fc7542aa","timestamp":1569638114701,"app_id":"com.nike.ntc.brand.droid","source":"nike.ntc.android"},{"key":"drill_start","value":"42eeecc9-cee9-36af-a50f-3277cbf4a0b4","timestamp":1569638124979,"app_id":"com.nike.ntc.brand.droid","source":"nike.ntc.android"},{"key":"drill_start","value":"ffeabcb9-f846-3718-9d0e-e562b5ef7e94","timestamp":1569638144874,"app_id":"com.nike.ntc.brand.droid","source":"nike.ntc.android"},{"key":"drill_start","value":"42eeecc9-cee9-36af-a50f-3277cbf4a0b4","timestamp":1569638169117,"app_id":"com.nike.ntc.brand.droid","source":"nike.ntc.android"},{"key":"drill_start","value":"63feb440-ee4f-3d4f-ba79-b9a12108f84b","timestamp":1569638203311,"app_id":"com.nike.ntc.brand.droid","source":"nike.ntc.android"},{"key":"drill_start","value":"42eeecc9-cee9-36af-a50f-3277cbf4a0b4","timestamp":1569638206390,"app_id":"com.nike.ntc.brand.droid","source":"nike.ntc.android"},{"key":"drill_start","value":"e68f3548-c9ec-3aed-ae74-8b9262a02feb","timestamp":1569638265270,"app_id":"com.nike.ntc.brand.droid","source":"nike.ntc.android"},{"key":"drill_start","value":"42eeecc9-cee9-36af-a50f-3277cbf4a0b4","timestamp":1569638273146,"app_id":"com.nike.ntc.brand.droid","source":"nike.ntc.android"},{"key":"drill_start","value":"f5f90453-2962-3faf-92ed-895888e265f3","timestamp":1569638305482,"app_id":"com.nike.ntc.brand.droid","source":"nike.ntc.android"},{"key":"drill_start","value":"42eeecc9-cee9-36af-a50f-3277cbf4a0b4","timestamp":1569638307356,"app_id":"com.nike.ntc.brand.droid","source":"nike.ntc.android"},{"key":"drill_start","value":"a349b942-3950-3da0-b20e-d6e833f4cc4a","timestamp":1569638345645,"app_id":"com.nike.ntc.brand.droid","source":"nike.ntc.android"},{"key":"drill_start","value":"42eeecc9-cee9-36af-a50f-3277cbf4a0b4","timestamp":1569638347497,"app_id":"com.nike.ntc.brand.droid","source":"nike.ntc.android"},{"key":"drill_start","value":"bc1946b6-fe1d-3f97-bac7-f0ec3fb70338","timestamp":1569638385880,"app_id":"com.nike.ntc.brand.droid","source":"nike.ntc.android"},{"key":"drill_start","value":"42eeecc9-cee9-36af-a50f-3277cbf4a0b4","timestamp":1569638390627,"app_id":"com.nike.ntc.brand.droid","source":"nike.ntc.android"},{"key":"drill_start","value":"502127f7-b89b-35e0-b684-14c70802ae32","timestamp":1569638426135,"app_id":"com.nike.ntc.brand.droid","source":"nike.ntc.android"},{"key":"drill_start","value":"42eeecc9-cee9-36af-a50f-3277cbf4a0b4","timestamp":1569638430650,"app_id":"com.nike.ntc.brand.droid","source":"nike.ntc.android"},{"key":"drill_start","value":"6b2fa117-d6a6-3de4-84cc-830371fe28b3","timestamp":1569638466389,"app_id":"com.nike.ntc.brand.droid","source":"nike.ntc.android"},{"key":"drill_start","value":"42eeecc9-cee9-36af-a50f-3277cbf4a0b4","timestamp":1569638480717,"app_id":"com.nike.ntc.brand.droid","source":"nike.ntc.android"},{"key":"drill_start","value":"5b4af1c8-bf84-39d5-89c3-b9371b517691","timestamp":1569638506313,"app_id":"com.nike.ntc.brand.droid","source":"nike.ntc.android"},{"key":"drill_start","value":"42eeecc9-cee9-36af-a50f-3277cbf4a0b4","timestamp":1569638514528,"app_id":"com.nike.ntc.brand.droid","source":"nike.ntc.android"},{"key":"drill_start","value":"bbaaa1f1-9f1e-3bd1-a9f0-b7881247ff16","timestamp":1569638546507,"app_id":"com.nike.ntc.brand.droid","source":"nike.ntc.android"},{"key":"drill_start","value":"42eeecc9-cee9-36af-a50f-3277cbf4a0b4","timestamp":1569638548568,"app_id":"com.nike.ntc.brand.droid","source":"nike.ntc.android"},{"key":"drill_start","value":"dedb2bef-120b-36bc-a7e4-56abca95d48b","timestamp":1569638598698,"app_id":"com.nike.ntc.brand.droid","source":"nike.ntc.android"},{"key":"drill_start","value":"42eeecc9-cee9-36af-a50f-3277cbf4a0b4","timestamp":1569638608836,"app_id":"com.nike.ntc.brand.droid","source":"nike.ntc.android"},{"key":"drill_start","value":"42eeecc9-cee9-36af-a50f-3277cbf4a0b4","timestamp":1569638633153,"app_id":"com.nike.ntc.brand.droid","source":"nike.ntc.android"},{"key":"drill_start","value":"42eeecc9-cee9-36af-a50f-3277cbf4a0b4","timestamp":1569638637293,"app_id":"com.nike.ntc.brand.droid","source":"nike.ntc.android"},{"key":"drill_start","value":"a88a21c6-cf2b-316d-a752-8def0dc25d1c","timestamp":1569638647089,"app_id":"com.nike.ntc.brand.droid","source":"nike.ntc.android"},{"key":"drill_start","value":"42eeecc9-cee9-36af-a50f-3277cbf4a0b4","timestamp":1569638655203,"app_id":"com.nike.ntc.brand.droid","source":"nike.ntc.android"},{"key":"drill_start","value":"7f5f37e9-bd3b-3c2b-a117-493ee45b3767","timestamp":1569638687332,"app_id":"com.nike.ntc.brand.droid","source":"nike.ntc.android"},{"key":"drill_start","value":"42eeecc9-cee9-36af-a50f-3277cbf4a0b4","timestamp":1569638696114,"app_id":"com.nike.ntc.brand.droid","source":"nike.ntc.android"},{"key":"drill_start","value":"de5ec438-6cdb-38f0-ac74-9a00dcc19030","timestamp":1569638727263,"app_id":"com.nike.ntc.brand.droid","source":"nike.ntc.android"},{"key":"drill_start","value":"42eeecc9-cee9-36af-a50f-3277cbf4a0b4","timestamp":1569638729357,"app_id":"com.nike.ntc.brand.droid","source":"nike.ntc.android"},{"key":"drill_start","value":"bf2856b6-90fe-34a0-a349-8fbd2830753d","timestamp":1569638767471,"app_id":"com.nike.ntc.brand.droid","source":"nike.ntc.android"},{"key":"drill_start","value":"42eeecc9-cee9-36af-a50f-3277cbf4a0b4","timestamp":1569638780498,"app_id":"com.nike.ntc.brand.droid","source":"nike.ntc.android"},{"key":"drill_start","value":"2a77a338-5a78-362e-b9ce-d6eadeca8198","timestamp":1569638807655,"app_id":"com.nike.ntc.brand.droid","source":"nike.ntc.android"},{"key":"drill_start","value":"42eeecc9-cee9-36af-a50f-3277cbf4a0b4","timestamp":1569638810122,"app_id":"com.nike.ntc.brand.droid","source":"nike.ntc.android"},{"key":"halt","value":"pause","timestamp":1569638146379,"app_id":"com.nike.ntc.brand.droid","source":"nike.ntc.android"},{"key":"halt","value":"resume","timestamp":1569638164892,"app_id":"com.nike.ntc.brand.droid","source":"nike.ntc.android"},{"key":"halt","value":"pause","timestamp":1569638239501,"app_id":"com.nike.ntc.brand.droid","source":"nike.ntc.android"},{"key":"halt","value":"resume","timestamp":1569638261519,"app_id":"com.nike.ntc.brand.droid","source":"nike.ntc.android"},{"key":"halt","value":"pause","timestamp":1569638584948,"app_id":"com.nike.ntc.brand.droid","source":"nike.ntc.android"},{"key":"halt","value":"resume","timestamp":1569638596948,"app_id":"com.nike.ntc.brand.droid","source":"nike.ntc.android"}]}